{
  "protocol_version" : "0.0.6",
  "configuration" : {
    "version" : "(6.13.0) (explicit/2db7aa41)",
    "tlc" : "__thread",
    "sigsgev" : "normal",
    "notifications" : "kqueue",
    "architecture" : "arm64",
    "disabled_features" : "com,shared_perfcounters",
    "smallconfig" : "disabled",
    "bigarrays" : "disabled",
    "softdebug" : "enabled",
    "interpreter" : "enabled",
    "llvm_support" : "disabled",
    "suspend" : "preemptive"
  },
  "memory" : {
    "Resident Size" : "131727360",
    "Virtual Size" : "421359157248",
    "minor_gc_time" : "0",
    "major_gc_time" : "440910",
    "minor_gc_count" : "0",
    "major_gc_count" : "5",
    "major_gc_time_concurrent" : "0"
 },
  "threads" : [
 {
    "is_managed" : false,
    "offset_free_hash" : "0x0",
    "offset_rich_hash" : "0x0",
    "crashed" : false,
    "native_thread_id" : "0x17f207000",
    "thread_info_addr" : "0x163127a00",
    "thread_name" : "Thread Pool I/O Selector",
    "ctx" : {
      "IP" : "0x184995a14",
      "SP" : "0x17f206ae0",
      "BP" : "0x17f206ce0"
  },
    "unmanaged_frames" : [
  {
      "is_managed" : "false",
      "native_address" : "0x153d055f8",
      "native_offset" : "0x00000"
   }
,
  {
      "is_managed" : "false",
      "native_address" : "0x153e3c6b8",
      "native_offset" : "0x00000"
   }
,
  {
      "is_managed" : "false",
      "native_address" : "0x153e3ca14",
      "native_offset" : "0x00000"
   }
,
  {
      "is_managed" : "false",
      "native_address" : "0x153e3c7dc",
      "native_offset" : "0x00000"
   }
,
  {
      "is_managed" : "false",
      "native_address" : "0x153d4660c",
      "native_offset" : "0x00000"
   }
,
  {
      "is_managed" : "false",
      "native_address" : "0x1849f9a24",
      "native_offset" : "0x00000"
   }
,
  {
      "is_managed" : "false",
      "native_address" : "0x153e8e910",
      "native_offset" : "0x00000"
   }
,
  {
      "is_managed" : "false",
      "native_address" : "0x153e41bf4",
      "native_offset" : "0x00000"
   }
,
  {
      "is_managed" : "false",
      "native_address" : "0x153e4160c",
      "native_offset" : "0x00000"
   }
,
  {
      "is_managed" : "false",
      "native_address" : "0x153e3d424",
      "native_offset" : "0x00000"
   }
,
  {
      "is_managed" : "false",
      "native_address" : "0x153e3d2d0",
      "native_offset" : "0x00000"
   }
,
  {
      "is_managed" : "false",
      "native_address" : "0x153ebcd18",
      "native_offset" : "0x00000"
   }
,
  {
      "is_managed" : "false",
      "native_address" : "0x153ebcca0",
      "native_offset" : "0x00000"
   }
,
  {
      "is_managed" : "false",
      "native_address" : "0x1849cb034",
      "native_offset" : "0x00000"
   }
,
  {
      "is_managed" : "false",
      "native_address" : "0x1849c5e3c",
      "native_offset" : "0x00000"
   }

  ]
 },
 {
    "is_managed" : false,
    "offset_free_hash" : "0x0",
    "offset_rich_hash" : "0x0",
    "crashed" : false,
    "native_thread_id" : "0x17bcab000",
    "thread_info_addr" : "0x2c2581e00",
    "thread_name" : "tid_14c03",
    "ctx" : {
      "IP" : "0x18498a830",
      "SP" : "0x17bcaad10",
      "BP" : "0x17bcaad20"
  },
    "unmanaged_frames" : [
  {
      "is_managed" : "false",
      "native_address" : "0x153d055f8",
      "native_offset" : "0x00000"
   }
,
  {
      "is_managed" : "false",
      "native_address" : "0x153e3c6b8",
      "native_offset" : "0x00000"
   }
,
  {
      "is_managed" : "false",
      "native_address" : "0x153e3ca14",
      "native_offset" : "0x00000"
   }
,
  {
      "is_managed" : "false",
      "native_address" : "0x153e3c7dc",
      "native_offset" : "0x00000"
   }
,
  {
      "is_managed" : "false",
      "native_address" : "0x153d4660c",
      "native_offset" : "0x00000"
   }
,
  {
      "is_managed" : "false",
      "native_address" : "0x1849f9a24",
      "native_offset" : "0x00000"
   }
,
  {
      "is_managed" : "false",
      "native_address" : "0x18481deac",
      "native_offset" : "0x00000"
   }
,
  {
      "is_managed" : "false",
      "native_address" : "0x18481e55c",
      "native_offset" : "0x00000"
   }
,
  {
      "is_managed" : "false",
      "native_address" : "0x1079303d8",
      "native_offset" : "0x00000"
   }
,
  {
      "is_managed" : "false",
      "native_address" : "0x105641734",
      "native_offset" : "0x00000"
   }
,
  {
      "is_managed" : "false",
      "native_address" : "0x105642918",
      "native_offset" : "0x00000"
   }
,
  {
      "is_managed" : "false",
      "native_address" : "0x1058a1ee4",
      "native_offset" : "0x00000"
   }
,
  {
      "is_managed" : "false",
      "native_address" : "0x1849cb034",
      "native_offset" : "0x00000"
   }
,
  {
      "is_managed" : "false",
      "native_address" : "0x1849c5e3c",
      "native_offset" : "0x00000"
   }

  ]
 },
 {
    "is_managed" : false,
    "offset_free_hash" : "0x0",
    "offset_rich_hash" : "0x0",
    "crashed" : false,
    "native_thread_id" : "0x17d82b000",
    "thread_info_addr" : "0x1578e8a00",
    "thread_name" : "Finalizer",
    "ctx" : {
      "IP" : "0x18498a830",
      "SP" : "0x17d82add0",
      "BP" : "0x17d82ae50"
  },
    "unmanaged_frames" : [
  {
      "is_managed" : "false",
      "native_address" : "0x153d055f8",
      "native_offset" : "0x00000"
   }
,
  {
      "is_managed" : "false",
      "native_address" : "0x153e3c6b8",
      "native_offset" : "0x00000"
   }
,
  {
      "is_managed" : "false",
      "native_address" : "0x153e3ca14",
      "native_offset" : "0x00000"
   }
,
  {
      "is_managed" : "false",
      "native_address" : "0x153e3c7dc",
      "native_offset" : "0x00000"
   }
,
  {
      "is_managed" : "false",
      "native_address" : "0x153d4660c",
      "native_offset" : "0x00000"
   }
,
  {
      "is_managed" : "false",
      "native_address" : "0x1849f9a24",
      "native_offset" : "0x00000"
   }
,
  {
      "is_managed" : "false",
      "native_address" : "0x153e7626c",
      "native_offset" : "0x00000"
   }
,
  {
      "is_managed" : "false",
      "native_address" : "0x153e3d424",
      "native_offset" : "0x00000"
   }
,
  {
      "is_managed" : "false",
      "native_address" : "0x153e3d2d0",
      "native_offset" : "0x00000"
   }
,
  {
      "is_managed" : "false",
      "native_address" : "0x153ebcd18",
      "native_offset" : "0x00000"
   }
,
  {
      "is_managed" : "false",
      "native_address" : "0x153ebcca0",
      "native_offset" : "0x00000"
   }
,
  {
      "is_managed" : "false",
      "native_address" : "0x1849cb034",
      "native_offset" : "0x00000"
   }
,
  {
      "is_managed" : "false",
      "native_address" : "0x1849c5e3c",
      "native_offset" : "0x00000"
   }

  ]
 },
 {
    "is_managed" : false,
    "offset_free_hash" : "0x0",
    "offset_rich_hash" : "0x0",
    "crashed" : false,
    "native_thread_id" : "0x17da37000",
    "thread_info_addr" : "0x1578bac00",
    "thread_name" : "Debugger agent",
    "ctx" : {
      "IP" : "0x184993200",
      "SP" : "0x17da36aa0",
      "BP" : "0x17da36ae0"
  },
    "unmanaged_frames" : [
  {
      "is_managed" : "false",
      "native_address" : "0x153d055f8",
      "native_offset" : "0x00000"
   }
,
  {
      "is_managed" : "false",
      "native_address" : "0x153e3c6b8",
      "native_offset" : "0x00000"
   }
,
  {
      "is_managed" : "false",
      "native_address" : "0x153e3ca14",
      "native_offset" : "0x00000"
   }
,
  {
      "is_managed" : "false",
      "native_address" : "0x153e3c7dc",
      "native_offset" : "0x00000"
   }
,
  {
      "is_managed" : "false",
      "native_address" : "0x153d4660c",
      "native_offset" : "0x00000"
   }
,
  {
      "is_managed" : "false",
      "native_address" : "0x1849f9a24",
      "native_offset" : "0x00000"
   }
,
  {
      "is_managed" : "false",
      "native_address" : "0x153d757c8",
      "native_offset" : "0x00000"
   }
,
  {
      "is_managed" : "false",
      "native_address" : "0x153d6c3c4",
      "native_offset" : "0x00000"
   }
,
  {
      "is_managed" : "false",
      "native_address" : "0x153e3d424",
      "native_offset" : "0x00000"
   }
,
  {
      "is_managed" : "false",
      "native_address" : "0x153e3d2d0",
      "native_offset" : "0x00000"
   }
,
  {
      "is_managed" : "false",
      "native_address" : "0x153ebcd18",
      "native_offset" : "0x00000"
   }
,
  {
      "is_managed" : "false",
      "native_address" : "0x153ebcca0",
      "native_offset" : "0x00000"
   }
,
  {
      "is_managed" : "false",
      "native_address" : "0x1849cb034",
      "native_offset" : "0x00000"
   }
,
  {
      "is_managed" : "false",
      "native_address" : "0x1849c5e3c",
      "native_offset" : "0x00000"
   }

  ]
 },
 {
    "is_managed" : false,
    "offset_free_hash" : "0x0",
    "offset_rich_hash" : "0x0",
    "crashed" : true,
    "native_thread_id" : "0x1dbc91300",
    "thread_info_addr" : "0x155922e00",
    "thread_name" : "tid_103",
    "ctx" : {
      "IP" : "0x106d93d24",
      "SP" : "0x16b09b4e0",
      "BP" : "0x16b09b500"
  },
    "unmanaged_frames" : [
  {
      "is_managed" : "false",
      "native_address" : "0x153d055f8",
      "native_offset" : "0x00000"
   }
,
  {
      "is_managed" : "false",
      "native_address" : "0x153e3c6b8",
      "native_offset" : "0x00000"
   }
,
  {
      "is_managed" : "false",
      "native_address" : "0x153e3ca14",
      "native_offset" : "0x00000"
   }
,
  {
      "is_managed" : "false",
      "native_address" : "0x153e3d004",
      "native_offset" : "0x00000"
   }
,
  {
      "is_managed" : "false",
      "native_address" : "0x153d47458",
      "native_offset" : "0x00000"
   }
,
  {
      "is_managed" : "false",
      "native_address" : "0x153d09790",
      "native_offset" : "0x00000"
   }
,
  {
      "is_managed" : "false",
      "native_address" : "0x153c91eb8",
      "native_offset" : "0x00000"
   }
,
  {
      "is_managed" : "false",
      "native_address" : "0x1849f9a24",
      "native_offset" : "0x00000"
   }
,
  {
      "is_managed" : "false",
      "native_address" : "0x106d93d24",
      "native_offset" : "0x00000"
   }
,
  {
      "is_managed" : "false",
      "native_address" : "0x106d472b8",
      "native_offset" : "0x00000"
   }
,
  {
      "is_managed" : "false",
      "native_address" : "0x106dddb38",
      "native_offset" : "0x00000"
   }
,
  {
      "is_managed" : "false",
      "native_address" : "0x106dbeed4",
      "native_offset" : "0x00000"
   }
,
  {
      "is_managed" : "false",
      "native_address" : "0x106dc0d00",
      "native_offset" : "0x00000"
   }
,
  {
      "is_managed" : "false",
      "native_address" : "0x106d33b10",
      "native_offset" : "0x00000"
   }
,
  {
      "is_managed" : "false",
      "native_address" : "0x1065f08f4",
      "native_offset" : "0x00000"
   }
,
  {
      "is_managed" : "false",
      "native_address" : "0x10786fe60",
      "native_offset" : "0x00000"
   }
,
  {
      "is_managed" : "false",
      "native_address" : "0x184a9c780",
      "native_offset" : "0x00000"
   }
,
  {
      "is_managed" : "false",
      "native_address" : "0x184b309a8",
      "native_offset" : "0x00000"
   }
,
  {
      "is_managed" : "false",
      "native_address" : "0x184b308f0",
      "native_offset" : "0x00000"
   }
,
  {
      "is_managed" : "false",
      "native_address" : "0x184a6b434",
      "native_offset" : "0x00000"
   }
,
  {
      "is_managed" : "false",
      "native_address" : "0x185b5cc74",
      "native_offset" : "0x00000"
   }
,
  {
      "is_managed" : "false",
      "native_address" : "0x1883d1fb0",
      "native_offset" : "0x00000"
   }
,
  {
      "is_managed" : "false",
      "native_address" : "0x188a53cb8",
      "native_offset" : "0x00000"
   }
,
  {
      "is_managed" : "false",
      "native_address" : "0x107888c0c",
      "native_offset" : "0x00000"
   }
,
  {
      "is_managed" : "false",
      "native_address" : "0x188421ab4",
      "native_offset" : "0x00000"
   }
,
  {
      "is_managed" : "false",
      "native_address" : "0x188420f9c",
      "native_offset" : "0x00000"
   }
,
  {
      "is_managed" : "false",
      "native_address" : "0x1883acb6c",
      "native_offset" : "0x00000"
   }
,
  {
      "is_managed" : "false",
      "native_address" : "0x1883ac82c",
      "native_offset" : "0x00000"
   }
,
  {
      "is_managed" : "false",
      "native_address" : "0x188a53c08",
      "native_offset" : "0x00000"
   }
,
  {
      "is_managed" : "false",
      "native_address" : "0x107888c0c",
      "native_offset" : "0x00000"
   }
,
  {
      "is_managed" : "false",
      "native_address" : "0x107870dac",
      "native_offset" : "0x00000"
   }
,
  {
      "is_managed" : "false",
      "native_address" : "0x185be78e8",
      "native_offset" : "0x00000"
   }
,
  {
      "is_managed" : "false",
      "native_address" : "0x184ac3d94",
      "native_offset" : "0x00000"
   }
,
  {
      "is_managed" : "false",
      "native_address" : "0x184ac3a3c",
      "native_offset" : "0x00000"
   }
,
  {
      "is_managed" : "false",
      "native_address" : "0x184ac3574",
      "native_offset" : "0x00000"
   }
,
  {
      "is_managed" : "false",
      "native_address" : "0x184aa6a20",
      "native_offset" : "0x00000"
   }
,
  {
      "is_managed" : "false",
      "native_address" : "0x184aa5c2c",
      "native_offset" : "0x00000"
   }
,
  {
      "is_managed" : "false",
      "native_address" : "0x18effe448",
      "native_offset" : "0x00000"
   }
,
  {
      "is_managed" : "false",
      "native_address" : "0x18effe0d8",
      "native_offset" : "0x00000"
   }
,
  {
      "is_managed" : "false",
      "native_address" : "0x18effdfdc",
      "native_offset" : "0x00000"
   }
,
  {
      "is_managed" : "false",
      "native_address" : "0x188280f90",
      "native_offset" : "0x00000"
   }
,
  {
      "is_managed" : "false",
      "native_address" : "0x188a54b94",
      "native_offset" : "0x00000"
   }
,
  {
      "is_managed" : "false",
      "native_address" : "0x18827443c",
      "native_offset" : "0x00000"
   }
,
  {
      "is_managed" : "false",
      "native_address" : "0x18824b708",
      "native_offset" : "0x00000"
   }
,
  {
      "is_managed" : "false",
      "native_address" : "0x107889480",
      "native_offset" : "0x00000"
   }
,
  {
      "is_managed" : "false",
      "native_address" : "0x1078897cc",
      "native_offset" : "0x00000"
   }
,
  {
      "is_managed" : "false",
      "native_address" : "0x184651058",
      "native_offset" : "0x00000"
   }

  ]
 },
 {
    "is_managed" : false,
    "offset_free_hash" : "0x0",
    "offset_rich_hash" : "0x0",
    "crashed" : false,
    "native_thread_id" : "0x17bc1f000",
    "thread_info_addr" : "0x16457dc00",
    "thread_name" : "tid_10f0f",
    "ctx" : {
      "IP" : "0x18498a830",
      "SP" : "0x17bc1ed10",
      "BP" : "0x17bc1ed20"
  },
    "unmanaged_frames" : [
  {
      "is_managed" : "false",
      "native_address" : "0x153d055f8",
      "native_offset" : "0x00000"
   }
,
  {
      "is_managed" : "false",
      "native_address" : "0x153e3c6b8",
      "native_offset" : "0x00000"
   }
,
  {
      "is_managed" : "false",
      "native_address" : "0x153e3ca14",
      "native_offset" : "0x00000"
   }
,
  {
      "is_managed" : "false",
      "native_address" : "0x153e3c7dc",
      "native_offset" : "0x00000"
   }
,
  {
      "is_managed" : "false",
      "native_address" : "0x153d4660c",
      "native_offset" : "0x00000"
   }
,
  {
      "is_managed" : "false",
      "native_address" : "0x1849f9a24",
      "native_offset" : "0x00000"
   }
,
  {
      "is_managed" : "false",
      "native_address" : "0x18481deac",
      "native_offset" : "0x00000"
   }
,
  {
      "is_managed" : "false",
      "native_address" : "0x18481e55c",
      "native_offset" : "0x00000"
   }
,
  {
      "is_managed" : "false",
      "native_address" : "0x1079303d8",
      "native_offset" : "0x00000"
   }
,
  {
      "is_managed" : "false",
      "native_address" : "0x105641734",
      "native_offset" : "0x00000"
   }
,
  {
      "is_managed" : "false",
      "native_address" : "0x105642918",
      "native_offset" : "0x00000"
   }
,
  {
      "is_managed" : "false",
      "native_address" : "0x1058a1ee4",
      "native_offset" : "0x00000"
   }
,
  {
      "is_managed" : "false",
      "native_address" : "0x1849cb034",
      "native_offset" : "0x00000"
   }
,
  {
      "is_managed" : "false",
      "native_address" : "0x1849c5e3c",
      "native_offset" : "0x00000"
   }

  ]
 }
 ]
}